odoo/addons/document_page_approval/README.rst
odoo/addons/document_page_approval/__init__.py
odoo/addons/document_page_approval/__manifest__.py
odoo/addons/document_page_approval/hooks.py
odoo/addons/document_page_approval/data/email_template.xml
odoo/addons/document_page_approval/i18n/am.po
odoo/addons/document_page_approval/i18n/ar.po
odoo/addons/document_page_approval/i18n/bg.po
odoo/addons/document_page_approval/i18n/bs.po
odoo/addons/document_page_approval/i18n/ca.po
odoo/addons/document_page_approval/i18n/cs.po
odoo/addons/document_page_approval/i18n/da.po
odoo/addons/document_page_approval/i18n/de.po
odoo/addons/document_page_approval/i18n/document_page_approval.pot
odoo/addons/document_page_approval/i18n/el.po
odoo/addons/document_page_approval/i18n/en_AU.po
odoo/addons/document_page_approval/i18n/en_GB.po
odoo/addons/document_page_approval/i18n/es.po
odoo/addons/document_page_approval/i18n/es_AR.po
odoo/addons/document_page_approval/i18n/es_CL.po
odoo/addons/document_page_approval/i18n/es_CO.po
odoo/addons/document_page_approval/i18n/es_CR.po
odoo/addons/document_page_approval/i18n/es_DO.po
odoo/addons/document_page_approval/i18n/es_EC.po
odoo/addons/document_page_approval/i18n/es_ES.po
odoo/addons/document_page_approval/i18n/es_MX.po
odoo/addons/document_page_approval/i18n/es_PY.po
odoo/addons/document_page_approval/i18n/es_VE.po
odoo/addons/document_page_approval/i18n/et.po
odoo/addons/document_page_approval/i18n/eu.po
odoo/addons/document_page_approval/i18n/fa.po
odoo/addons/document_page_approval/i18n/fi.po
odoo/addons/document_page_approval/i18n/fr.po
odoo/addons/document_page_approval/i18n/fr_CA.po
odoo/addons/document_page_approval/i18n/gl.po
odoo/addons/document_page_approval/i18n/gu.po
odoo/addons/document_page_approval/i18n/he.po
odoo/addons/document_page_approval/i18n/hi.po
odoo/addons/document_page_approval/i18n/hr.po
odoo/addons/document_page_approval/i18n/hu.po
odoo/addons/document_page_approval/i18n/hy.po
odoo12_addon_document_page_approval-12.0.1.0.5.dist-info/METADATA
odoo12_addon_document_page_approval-12.0.1.0.5.dist-info/WHEEL
odoo12_addon_document_page_approval-12.0.1.0.5.dist-info/top_level.txt
odoo12_addon_document_page_approval-12.0.1.0.5.dist-info/RECORD
