Metadata-Version: 2.1
Name: odoo12-addon-document-page-approval
Version: 12.0.1.0.5
Summary: Document Page Approval
Home-page: http://www.savoirfairelinux.com
Author: Savoir-faire Linux, Odoo Community Association (OCA)
Author-email: support@odoo-community.org
License: AGPL-3
Platform: UNKNOWN
Classifier: Programming Language :: Python
Classifier: Framework :: Odoo
Classifier: License :: OSI Approved :: GNU Affero General Public License v3
Requires-Python: >=3.5
Requires-Dist: odoo12-addon-document-page
Requires-Dist: odoo (<12.1dev,>=12.0a)
